gmopg/__init__.py
gmopg/_helpers.py
gmopg/api.py
gmopg/context.py
gmopg/errors.py
gmopg/exceptions.py
gmopg/response.py
gmopg-0.0.6.dist-info/DESCRIPTION.rst
gmopg-0.0.6.dist-info/METADATA
gmopg-0.0.6.dist-info/RECORD
gmopg-0.0.6.dist-info/WHEEL
gmopg-0.0.6.dist-info/metadata.json
gmopg-0.0.6.dist-info/top_level.txt
