Metadata-Version: 2.0
Name: gmopg
Version: 0.0.6
Summary: Python API Client for GMO Payment Gateway
Home-page: https://github.com/a-r-g-v/gmo-payment-python
Author: a_r_g_v
Author-email: info@arg.vc
License: MIT
Keywords: gmopg
Platform: UNKNOWN
Requires-Dist: requests
Requires-Dist: six
Requires-Dist: typing
